nonebot_plugin_kawaii_robot-4.1.4.dist-info/METADATA
nonebot_plugin_kawaii_robot-4.1.4.dist-info/WHEEL
nonebot_plugin_kawaii_robot-4.1.4.dist-info/entry_points.txt
nonebot_plugin_kawaii_robot-4.1.4.dist-info/licenses/LICENSE
nonebot_plugin_kawaii_robot/__init__.py
nonebot_plugin_kawaii_robot/__main__.py
nonebot_plugin_kawaii_robot/config.py
nonebot_plugin_kawaii_robot/const.py
nonebot_plugin_kawaii_robot/data_source.py
nonebot_plugin_kawaii_robot/resource/data.json
nonebot_plugin_kawaii_robot/resource/leaf.json
nonebot_plugin_kawaii_robot/utils.py
nonebot_plugin_kawaii_robot-4.1.4.dist-info/RECORD
