Metadata-Version: 2.1
Name: nonebot-plugin-kawaii-robot
Version: 4.1.4
Summary: 使用 Kyomotoi/AnimeThesaurus 的 NoneBot2 的回复（文i）插件
Author-Email: karisaya <1048827424@qq.com>, LgCookie <lgc2333@126.com>
License: AGPL-3.0
Project-URL: homepage, https://github.com/KarisAya/nonebot_plugin_kawaii_robot/
Requires-Python: <4.0,>=3.10
Requires-Dist: nonebot2>=2.4.3
Requires-Dist: nonebot-plugin-alconna>=0.59.4
Requires-Dist: nonebot-plugin-uninfo>=0.9.0
Requires-Dist: nonebot-plugin-localstore>=0.7.4
Requires-Dist: cookit[pydantic]>=0.13.0
Requires-Dist: anyio>=4.10.0
